[
  {
    "inputs": [],
    "name": "AlreadyClaimed",
    "type": "error"
  },
  {
    "inputs": [],
    "name": "IndexOutOfBounds",
    "type": "error"
  },
  {
    "inputs": [],
    "name": "InvalidInput",
    "type": "error"
  },
  {
    "inputs": [],
    "name": "NotClosed",
    "type": "error"
  },
  {
    "inputs": [],
    "name": "NotCreator",
    "type": "error"
  },
  {
    "inputs": [],
    "name": "NotFound",
    "type": "error"
  },
  {
    "inputs": [],
    "name": "NotOpen",
    "type": "error"
  },
  {
    "inputs": [],
    "name": "NotRevealed",
    "type": "error"
  },
  {
    "inputs": [],
    "name": "NotWinner",
    "type": "error"
  },
  {
    "inputs": [],
    "name": "ReentrancyGuardReentrantCall",
    "type": "error"
  },
  {
    "inputs": [
      {
        "internalType": "address",
        "name": "token",
        "type": "address"
      }
    ],
    "name": "SafeERC20FailedOperation",
    "type": "error"
  },
  {
    "inputs": [
      {
        "internalType": "int32",
        "name": "value",
        "type": "int32"
      }
    ],
    "name": "SecurityZoneOutOfBounds",
    "type": "error"
  },
  {
    "inputs": [],
    "name": "TicketLimit",
    "type": "error"
  },
  {
    "inputs": [],
    "name": "TooEarly",
    "type": "error"
  },
  {
    "anonymous": false,
    "inputs": [
      {
        "indexed": true,
        "internalType": "uint256",
        "name": "id",
        "type": "uint256"
      },
      {
        "indexed": true,
        "internalType": "address",
        "name": "winner",
        "type": "address"
      },
      {
        "indexed": false,
        "internalType": "uint256",
        "name": "prize",
        "type": "uint256"
      }
    ],
    "name": "PrizeClaimed",
    "type": "event"
  },
  {
    "anonymous": false,
    "inputs": [
      {
        "indexed": true,
        "internalType": "uint256",
        "name": "id",
        "type": "uint256"
      }
    ],
    "name": "RaffleCancelled",
    "type": "event"
  },
  {
    "anonymous": false,
    "inputs": [
      {
        "indexed": true,
        "internalType": "uint256",
        "name": "id",
        "type": "uint256"
      },
      {
        "indexed": true,
        "internalType": "address",
        "name": "creator",
        "type": "address"
      },
      {
        "indexed": true,
        "internalType": "address",
        "name": "token",
        "type": "address"
      },
      {
        "indexed": false,
        "internalType": "uint256",
        "name": "ticketPrice",
        "type": "uint256"
      },
      {
        "indexed": false,
        "internalType": "uint64",
        "name": "maxTickets",
        "type": "uint64"
      },
      {
        "indexed": false,
        "internalType": "uint64",
        "name": "deadline",
        "type": "uint64"
      }
    ],
    "name": "RaffleCreated",
    "type": "event"
  },
  {
    "anonymous": false,
    "inputs": [
      {
        "indexed": true,
        "internalType": "uint256",
        "name": "id",
        "type": "uint256"
      },
      {
        "indexed": true,
        "internalType": "address",
        "name": "buyer",
        "type": "address"
      },
      {
        "indexed": false,
        "internalType": "uint64",
        "name": "ticketNumber",
        "type": "uint64"
      }
    ],
    "name": "TicketBought",
    "type": "event"
  },
  {
    "anonymous": false,
    "inputs": [
      {
        "indexed": true,
        "internalType": "uint256",
        "name": "id",
        "type": "uint256"
      }
    ],
    "name": "WinnerDrawn",
    "type": "event"
  },
  {
    "anonymous": false,
    "inputs": [
      {
        "indexed": true,
        "internalType": "uint256",
        "name": "id",
        "type": "uint256"
      },
      {
        "indexed": true,
        "internalType": "address",
        "name": "winner",
        "type": "address"
      },
      {
        "indexed": false,
        "internalType": "uint64",
        "name": "index",
        "type": "uint64"
      }
    ],
    "name": "WinnerRevealed",
    "type": "event"
  },
  {
    "inputs": [],
    "name": "MAX_TICKETS",
    "outputs": [
      {
        "internalType": "uint64",
        "name": "",
        "type": "uint64"
      }
    ],
    "stateMutability": "view",
    "type": "function"
  },
  {
    "inputs": [
      {
        "internalType": "uint256",
        "name": "id",
        "type": "uint256"
      }
    ],
    "name": "buyTicket",
    "outputs": [],
    "stateMutability": "nonpayable",
    "type": "function"
  },
  {
    "inputs": [
      {
        "internalType": "uint256",
        "name": "id",
        "type": "uint256"
      }
    ],
    "name": "cancelEmpty",
    "outputs": [],
    "stateMutability": "nonpayable",
    "type": "function"
  },
  {
    "inputs": [
      {
        "internalType": "uint256",
        "name": "id",
        "type": "uint256"
      }
    ],
    "name": "claimPrize",
    "outputs": [],
    "stateMutability": "nonpayable",
    "type": "function"
  },
  {
    "inputs": [
      {
        "internalType": "address",
        "name": "token",
        "type": "address"
      },
      {
        "internalType": "uint256",
        "name": "ticketPrice",
        "type": "uint256"
      },
      {
        "internalType": "uint64",
        "name": "maxTickets",
        "type": "uint64"
      },
      {
        "internalType": "uint64",
        "name": "duration",
        "type": "uint64"
      }
    ],
    "name": "createRaffle",
    "outputs": [
      {
        "internalType": "uint256",
        "name": "id",
        "type": "uint256"
      }
    ],
    "stateMutability": "nonpayable",
    "type": "function"
  },
  {
    "inputs": [
      {
        "internalType": "uint256",
        "name": "id",
        "type": "uint256"
      }
    ],
    "name": "drawWinner",
    "outputs": [],
    "stateMutability": "nonpayable",
    "type": "function"
  },
  {
    "inputs": [
      {
        "internalType": "uint256",
        "name": "id",
        "type": "uint256"
      }
    ],
    "name": "getEncWinnerIndex",
    "outputs": [
      {
        "internalType": "euint64",
        "name": "",
        "type": "bytes32"
      }
    ],
    "stateMutability": "view",
    "type": "function"
  },
  {
    "inputs": [
      {
        "internalType": "uint256",
        "name": "id",
        "type": "uint256"
      }
    ],
    "name": "getParticipants",
    "outputs": [
      {
        "internalType": "address[]",
        "name": "",
        "type": "address[]"
      }
    ],
    "stateMutability": "view",
    "type": "function"
  },
  {
    "inputs": [],
    "name": "getRaffleCount",
    "outputs": [
      {
        "internalType": "uint256",
        "name": "",
        "type": "uint256"
      }
    ],
    "stateMutability": "view",
    "type": "function"
  },
  {
    "inputs": [],
    "name": "raffleCount",
    "outputs": [
      {
        "internalType": "uint256",
        "name": "",
        "type": "uint256"
      }
    ],
    "stateMutability": "view",
    "type": "function"
  },
  {
    "inputs": [
      {
        "internalType": "uint256",
        "name": "",
        "type": "uint256"
      }
    ],
    "name": "raffles",
    "outputs": [
      {
        "internalType": "address",
        "name": "creator",
        "type": "address"
      },
      {
        "internalType": "address",
        "name": "token",
        "type": "address"
      },
      {
        "internalType": "uint256",
        "name": "ticketPrice",
        "type": "uint256"
      },
      {
        "internalType": "uint64",
        "name": "maxTickets",
        "type": "uint64"
      },
      {
        "internalType": "uint64",
        "name": "ticketCount",
        "type": "uint64"
      },
      {
        "internalType": "uint64",
        "name": "deadline",
        "type": "uint64"
      },
      {
        "internalType": "address",
        "name": "winner",
        "type": "address"
      },
      {
        "internalType": "uint64",
        "name": "winnerIndex",
        "type": "uint64"
      },
      {
        "internalType": "enum EncryptedRaffle.RaffleStatus",
        "name": "status",
        "type": "uint8"
      }
    ],
    "stateMutability": "view",
    "type": "function"
  },
  {
    "inputs": [
      {
        "internalType": "uint256",
        "name": "id",
        "type": "uint256"
      },
      {
        "internalType": "uint64",
        "name": "winnerIndex",
        "type": "uint64"
      },
      {
        "internalType": "bytes",
        "name": "sig",
        "type": "bytes"
      }
    ],
    "name": "revealWinner",
    "outputs": [],
    "stateMutability": "nonpayable",
    "type": "function"
  }
]